__init__.py
app/__init__.py
app/database.py
app/log_config.py
app/logger.py
app/main.py
app/model.py
happymeter-4.0.1.dist-info/licenses/LICENSE
streamlit/ui.py
tests/__init__.py
tests/test_database.py
tests/test_main.py
tests/test_model.py
tests/test_ui.py
happymeter-4.0.1.dist-info/METADATA
happymeter-4.0.1.dist-info/WHEEL
happymeter-4.0.1.dist-info/top_level.txt
happymeter-4.0.1.dist-info/RECORD
