Metadata-Version: 2.4
Name: happymeter
Version: 4.0.1
Summary: Find out how happy you are
Author-email: Klim Mikhailov <mixklim@gmail.com>
License: MIT
Requires-Python: ==3.12.*
License-File: LICENSE
Dynamic: license-file
